{
    "hash": "6d673a409e351526b3d51e15a01a9138742a88be55156883f28213dfde630066",
    "number": 847892,
    "previous": "d3f376c2e0e859df4c8d80b154a4e5870db63ba688bf6f3914a98bba655136f4",
    "subblocks": [
        {
            "input_hash": "b4b25c3af2e825857c6b6c8aac24b6a4ed7cb6b861b93282031c491d04544128",
            "merkle_leaves": [
                "27854fb257f970797f7a2e432637031228f65dc4b7ca0c16e8e4ea945192b09b"
            ],
            "signatures": [
                {
                    "signature": "dd154b3b8a35a4349124f8a41ef1fff0cdf26efda6bba0c8de1e79bd3a814701c24b433b81f9263be6601144fdc2ad3485e5527b5d1f0b100cd44cf31579a70f",
                    "signer": "2bdb7a98d65a469dacd93873ce3f8b6bb5284414348cab17ade738f913d35e32"
                },
                {
                    "signature": "b18037b3c82ed858e25f25adf214bd6aa8f32984c794b176cded042dfd1bd4ab0930b7c04f9be30f6597e3b556e56402723db54fdf9a3c28fb02465a8b93ce08",
                    "signer": "555100f02ef3bdc469e866140c35955e137624f4a1284bbcb999cd7fb576c869"
                }
            ],
            "subblock": 0,
            "transactions": [
                {
                    "hash": "e340736db23ac65325f899ddbe37fa5194ea8a067777ca28b425a3eb53d99982",
                    "result": "{'starting_epoch': 124, 'time': 2022-04-24 22:44:17, 'amount': Decimal('13570.744559501146268578837085886496')}",
                    "stamps_used": 139,
                    "state": [
                        {
                            "key": "con_rswp_lst001.balances:c4bd39cefae550f729ef7aea18591b7c9da0c64ae3b58a7b6ccc57d315adec85:con_staking_rswp_rswp_interop_v2",
                            "value": {
                                "__fixed__": "99999999999999999999999984946.76959814"
                            }
                        },
                        {
                            "key": "con_rswp_lst001.balances:c4bd39cefae550f729ef7aea18591b7c9da0c64ae3b58a7b6ccc57d315adec85",
                            "value": {
                                "__fixed__": "1.177299315699368385547E-9"
                            }
                        },
                        {
                            "key": "con_rswp_lst001.balances:con_staking_rswp_rswp_interop_v2",
                            "value": {
                                "__fixed__": "47786760.255415717565811185768412470521"
                            }
                        },
                        {
                            "key": "con_staking_rswp_rswp_interop_v2.decimal_converter_var",
                            "value": {
                                "__fixed__": "0.000231346816911115936109423581"
                            }
                        },
                        {
                            "key": "con_rswp_lst001.balances:7c296eb80e379171f694a3c5be7640d16f300f09d731c99ac0a92f49c9c0c151",
                            "value": {
                                "__fixed__": "5949084.161133201588218130604953324203"
                            }
                        },
                        {
                            "key": "con_staking_rswp_rswp_interop_v2.StakedBalance",
                            "value": {
                                "__fixed__": "55964541.465261825035599806747698659879"
                            }
                        },
                        {
                            "key": "con_staking_rswp_rswp_interop_v2.WithdrawnBalance",
                            "value": {
                                "__fixed__": "32077781.209846107469788620979286189358"
                            }
                        },
                        {
                            "key": "con_staking_rswp_rswp_interop_v2.balances:c4bd39cefae550f729ef7aea18591b7c9da0c64ae3b58a7b6ccc57d315adec85",
                            "value": {
                                "__fixed__": "13570.744559501146268578837085886496"
                            }
                        },
                        {
                            "key": "con_staking_rswp_rswp_interop_v2.Withdrawals:c4bd39cefae550f729ef7aea18591b7c9da0c64ae3b58a7b6ccc57d315adec85",
                            "value": 0
                        },
                        {
                            "key": "con_staking_rswp_rswp_interop_v2.Deposits:c4bd39cefae550f729ef7aea18591b7c9da0c64ae3b58a7b6ccc57d315adec85",
                            "value": {
                                "amount": {
                                    "__fixed__": "13570.744559501146268578837085886496"
                                },
                                "starting_epoch": 124,
                                "time": {
                                    "__time__": [
                                        2022,
                                        4,
                                        24,
                                        22,
                                        44,
                                        17,
                                        0
                                    ]
                                }
                            }
                        },
                        {
                            "key": "currency.balances:c4bd39cefae550f729ef7aea18591b7c9da0c64ae3b58a7b6ccc57d315adec85",
                            "value": {
                                "__fixed__": "170.611079479315973307193424035852"
                            }
                        }
                    ],
                    "status": 0,
                    "transaction": {
                        "metadata": {
                            "signature": "a4d4ca53357eceb744a028743e9b38a78b2121911853502b4d98a2c95192c62b98c30576e99a68d3a2f4428b6ac46618781805f01b1f15747f1d9d741b0b0300",
                            "timestamp": 1650840248
                        },
                        "payload": {
                            "contract": "con_staking_rswp_rswp_interop_v2",
                            "function": "addStakingTokens",
                            "kwargs": {
                                "amount": {
                                    "__fixed__": "707.86065158"
                                }
                            },
                            "nonce": 101,
                            "processor": "5b09493df6c18d17cc883ebce54fcb1f5afbd507533417fe32c006009a9c3c4a",
                            "sender": "c4bd39cefae550f729ef7aea18591b7c9da0c64ae3b58a7b6ccc57d315adec85",
                            "stamps_supplied": 533
                        }
                    }
                }
            ]
        }
    ]
}