{
    "hash": "edc8b45cb75c7797c17250e8350a77667b859aaf15dbae28c5193bfc54bd2c1c",
    "number": 848353,
    "previous": "481990d2e814ff0e45e3d7794ff9b98d541d8b95c716b5d4fc2ba804a0d00504",
    "subblocks": [
        {
            "input_hash": "47af510df23900a16512b0cd50175fbddfbe37b6e18e17f09b30b29cc35ffa41",
            "merkle_leaves": [
                "932c86730444a15adfaf643216ad022df2739db67fa03dbf4ad5ea5c5fd3133c"
            ],
            "signatures": [
                {
                    "signature": "4431b15dfb93a439701efe7e78ede4412c16ff33fbdb448d585ff94f5ddf2c7218d13309164847c7aaa7bd8571f0ed99900675e314a223f1043431a228ae0307",
                    "signer": "2bdb7a98d65a469dacd93873ce3f8b6bb5284414348cab17ade738f913d35e32"
                },
                {
                    "signature": "f5f4cd7a4086f61a0cb294b03eddfd87005a8d9e049635e53f8242d0fe7b6208c7d165de66b60a56f849d4aece250d09e35f70c8d7fe36af22a6354e5e83820f",
                    "signer": "555100f02ef3bdc469e866140c35955e137624f4a1284bbcb999cd7fb576c869"
                }
            ],
            "subblock": 0,
            "transactions": [
                {
                    "hash": "0d34c3fe31ecba5be289e3dbb173e265ee947a80cba540b37ccac9f92362fd3b",
                    "result": "Decimal('86.269057348551532126872511299600')",
                    "stamps_used": 126,
                    "state": [
                        {
                            "key": "con_rocketswap_official_v1_1.reserves:con_rswp_lst001",
                            "value": [
                                {
                                    "__fixed__": "2285738.358082758087758417520869631281"
                                },
                                {
                                    "__fixed__": "19635757.193087232883985798639732376045"
                                }
                            ]
                        },
                        {
                            "key": "con_rocketswap_official_v1_1.prices:con_rswp_lst001",
                            "value": {
                                "__fixed__": "0.116406937384999450726013555126"
                            }
                        },
                        {
                            "key": "con_rswp_lst001.balances:con_rocketswap_official_v1_1",
                            "value": {
                                "__fixed__": "19750470.050486322883985798639732415074"
                            }
                        },
                        {
                            "key": "con_rswp_lst001.balances:burn",
                            "value": {
                                "__fixed__": "720908829.409976230121479078663230861273"
                            }
                        },
                        {
                            "key": "con_reflecttau.balances:165fce0649c742e640ceb6ecb39a01c719fa5d39ee28016496aaed7709730805:con_rocketswap_official_v1_1",
                            "value": {
                                "__fixed__": "99999999999999999999999880000"
                            }
                        },
                        {
                            "key": "con_reflecttau.balances:165fce0649c742e640ceb6ecb39a01c719fa5d39ee28016496aaed7709730805",
                            "value": {
                                "__fixed__": "3310826.0"
                            }
                        },
                        {
                            "key": "con_reflecttau.balances:con_rocketswap_official_v1_1",
                            "value": {
                                "__fixed__": "45602135.50371814950718372262368167702"
                            }
                        },
                        {
                            "key": "currency.balances:con_rocketswap_official_v1_1",
                            "value": {
                                "__fixed__": "11617026.963931736390081580373025879217"
                            }
                        },
                        {
                            "key": "currency.balances:165fce0649c742e640ceb6ecb39a01c719fa5d39ee28016496aaed7709730805",
                            "value": {
                                "__fixed__": "5373.683557904559508640744516075409"
                            }
                        },
                        {
                            "key": "con_rocketswap_official_v1_1.reserves:con_reflecttau",
                            "value": [
                                {
                                    "__fixed__": "464.672165565099019262916719943689"
                                },
                                {
                                    "__fixed__": "762825.800532517004029174138251349371"
                                }
                            ]
                        },
                        {
                            "key": "con_rocketswap_official_v1_1.prices:con_reflecttau",
                            "value": {
                                "__fixed__": "0.000609145843311432963811512004"
                            }
                        }
                    ],
                    "status": 0,
                    "transaction": {
                        "metadata": {
                            "signature": "a3640edd1c2f8007ab2e31e915710a4e2961196d0ea3f09126d4afb0f692486e63883a62c672d77291d396c18d2df03c47180422e145cf7bd27c98c0d45b6a06",
                            "timestamp": 1650937210
                        },
                        "payload": {
                            "contract": "con_rocketswap_official_v1_1",
                            "function": "sell",
                            "kwargs": {
                                "contract": "con_reflecttau",
                                "minimum_received": {
                                    "__fixed__": "52.208844"
                                },
                                "token_amount": {
                                    "__fixed__": "120000"
                                },
                                "token_fees": false
                            },
                            "nonce": 131,
                            "processor": "5b09493df6c18d17cc883ebce54fcb1f5afbd507533417fe32c006009a9c3c4a",
                            "sender": "165fce0649c742e640ceb6ecb39a01c719fa5d39ee28016496aaed7709730805",
                            "stamps_supplied": 300
                        }
                    }
                }
            ]
        }
    ]
}