{
    "hash": "a3869ae89405f99023c405714a25172eb0ef942e3fc4617686baa685498975f9",
    "number": 848437,
    "previous": "07e1a23f11e17eb9583cbd2af4e4a3cd00b4a22e62ae37e2821587032eaa64ff",
    "subblocks": [
        {
            "input_hash": "7a4c8591f2fe8473ca3af5faa099ea83804615c2f251fceb5b7675cd4fc745be",
            "merkle_leaves": [
                "282416cb84e59542cc9895a03834eaf060cd14a72b0ea728a9a8ea5bb98995d4"
            ],
            "signatures": [
                {
                    "signature": "018ab303fc4136a7ee5505976b5b9e1cc6756ac79cca209309d784c456a15c21971fb2670a8d773bd21971df976457abccd727e697791d8b99c27a12a7d9450d",
                    "signer": "2bdb7a98d65a469dacd93873ce3f8b6bb5284414348cab17ade738f913d35e32"
                },
                {
                    "signature": "6585ef7bc026ea27f3b9c9565db13447f8c17a91417e95a75013bca79f81184a757704bc7377ff7eaa55e3ffd28e7382c93e7a64d248dae9fdf464caf4544308",
                    "signer": "b0fc27299da14bc08834df9c70d73074f3e511a5a91321d4fa413f3401144918"
                }
            ],
            "subblock": 0,
            "transactions": [
                {
                    "hash": "6c16f556a0310aa17436434da38f217367fd506d50105678ef5369143abb7f5a",
                    "result": "<contracting.stdlib.bridge.decimal.ContractingDecimal object>",
                    "stamps_used": 114,
                    "state": [
                        {
                            "key": "con_staking_rswp_rswp_interop_v2.decimal_converter_var",
                            "value": {
                                "__fixed__": "0.001270874499223181286038928536"
                            }
                        },
                        {
                            "key": "con_rswp_lst001.balances:con_staking_rswp_rswp_interop_v2",
                            "value": {
                                "__fixed__": "47814744.424353460868972859085654435075"
                            }
                        },
                        {
                            "key": "con_rswp_lst001.balances:7c296eb80e379171f694a3c5be7640d16f300f09d731c99ac0a92f49c9c0c151",
                            "value": {
                                "__fixed__": "5943207.296263659580851454472207297941"
                            }
                        },
                        {
                            "key": "con_rswp_lst001.balances:17aaf6f3292be287d04c68a7d62eaaf32632448b126cd73e47ad00f463984ba2",
                            "value": {
                                "__fixed__": "6244.682418403492135048350787211593"
                            }
                        },
                        {
                            "key": "con_staking_rswp_rswp_interop_v2.Withdrawals:17aaf6f3292be287d04c68a7d62eaaf32632448b126cd73e47ad00f463984ba2",
                            "value": {
                                "__fixed__": "2282.30642442"
                            }
                        },
                        {
                            "key": "con_staking_rswp_rswp_interop_v2.WithdrawnBalance",
                            "value": {
                                "__fixed__": "32153873.04243473931661013440873090529"
                            }
                        },
                        {
                            "key": "currency.balances:17aaf6f3292be287d04c68a7d62eaaf32632448b126cd73e47ad00f463984ba2",
                            "value": {
                                "__fixed__": "167.240930809054145530667340345573"
                            }
                        }
                    ],
                    "status": 0,
                    "transaction": {
                        "metadata": {
                            "signature": "fea398a6042e26998d73c5ffdf01bfa236cbefbbd2c11a701ce782f54482239a4128b603615fd5dfa456d3a2256bf01d4aeb93c60a63b643fe86509c03384e0c",
                            "timestamp": 1650959615
                        },
                        "payload": {
                            "contract": "con_staking_rswp_rswp_interop_v2",
                            "function": "withdrawYield",
                            "kwargs": {
                                "amount": {
                                    "__fixed__": "2282.30642442"
                                }
                            },
                            "nonce": 87,
                            "processor": "5b09493df6c18d17cc883ebce54fcb1f5afbd507533417fe32c006009a9c3c4a",
                            "sender": "17aaf6f3292be287d04c68a7d62eaaf32632448b126cd73e47ad00f463984ba2",
                            "stamps_supplied": 533
                        }
                    }
                }
            ]
        }
    ]
}