{
    "hash": "261b536529c6113904dfc4ffebcc2d57231281ed3ff00958ba8b44da7370e730",
    "number": 848482,
    "previous": "3f8e94e9f48b1b57ef0744cd5d8e7278b1fc8eb74f2fcaf7a1a892455aaca638",
    "subblocks": [
        {
            "input_hash": "b4acfd73fcec04dc8a0f82c139545ab4d49bb72da1b4ae6512be31586cc2d234",
            "merkle_leaves": [
                "23d7a05c0dd964e216071a053ed22964be7c002c6209c6abc98d9595dad420c4"
            ],
            "signatures": [
                {
                    "signature": "c800679eecd41b7bb4e992104ab504965d638b810a3f7e5dab3b2884bc68c215a6ba0762daa3359354f92072e0c4ba07a69c27413ca3f49f845f5b756e728e06",
                    "signer": "2bdb7a98d65a469dacd93873ce3f8b6bb5284414348cab17ade738f913d35e32"
                },
                {
                    "signature": "4fababfaefe2b883d8defaf23b85862583f4a8ac12840a65190258e8e25249247054aac7716f7051f65b7c355695b79709cd5c8f47545214cefcd138243c8101",
                    "signer": "555100f02ef3bdc469e866140c35955e137624f4a1284bbcb999cd7fb576c869"
                }
            ],
            "subblock": 0,
            "transactions": [
                {
                    "hash": "5e3012b5effba8119717f7e51e7a8258bddf65e964b9bfe42402121535a0c0bd",
                    "result": "Decimal('2951.785132423834602497276711181069')",
                    "stamps_used": 82,
                    "state": [
                        {
                            "key": "con_rswp_lst001.balances:9c18f33f197b9bc1e1f6347ba0a88dee9aed6429b88c41e9185b7b6994882005:con_rocketswap_official_v1_1",
                            "value": {
                                "__fixed__": "99999999999999999999999974136.34280306"
                            }
                        },
                        {
                            "key": "con_rswp_lst001.balances:9c18f33f197b9bc1e1f6347ba0a88dee9aed6429b88c41e9185b7b6994882005",
                            "value": {
                                "__fixed__": "5.423030931051407975185E-9"
                            }
                        },
                        {
                            "key": "con_rswp_lst001.balances:con_rocketswap_official_v1_1",
                            "value": {
                                "__fixed__": "19828598.540150424352835349574183266172"
                            }
                        },
                        {
                            "key": "con_rocketswap_official_v1_1.reserves:con_rswp_lst001",
                            "value": [
                                {
                                    "__fixed__": "2272172.794457266241640069633218941774"
                                },
                                {
                                    "__fixed__": "19713885.682751334352835349574183227139"
                                }
                            ]
                        },
                        {
                            "key": "con_rocketswap_official_v1_1.prices:con_rswp_lst001",
                            "value": {
                                "__fixed__": "0.115257480489769908016800248253"
                            }
                        },
                        {
                            "key": "currency.balances:con_rocketswap_official_v1_1",
                            "value": {
                                "__fixed__": "11622327.606147282331590804088096264053"
                            }
                        },
                        {
                            "key": "currency.balances:9c18f33f197b9bc1e1f6347ba0a88dee9aed6429b88c41e9185b7b6994882005",
                            "value": {
                                "__fixed__": "3004.198177378704204321858692845748"
                            }
                        }
                    ],
                    "status": 0,
                    "transaction": {
                        "metadata": {
                            "signature": "e335c7eb712bd32ec967cf9ff1c97aa2e72a96dca2443ec140583c0a10a9585ccdb91f9029d3ab4b8d7fcef0c3d33b0b0612c39d676044e64ca080d2844a7706",
                            "timestamp": 1650978892
                        },
                        "payload": {
                            "contract": "con_rocketswap_official_v1_1",
                            "function": "sell",
                            "kwargs": {
                                "contract": "con_rswp_lst001",
                                "minimum_received": {
                                    "__fixed__": "2940.78656339"
                                },
                                "token_amount": {
                                    "__fixed__": "25705.65719694"
                                },
                                "token_fees": true
                            },
                            "nonce": 41,
                            "processor": "5b09493df6c18d17cc883ebce54fcb1f5afbd507533417fe32c006009a9c3c4a",
                            "sender": "9c18f33f197b9bc1e1f6347ba0a88dee9aed6429b88c41e9185b7b6994882005",
                            "stamps_supplied": 195
                        }
                    }
                }
            ]
        }
    ]
}