{
    "hash": "3df8ad5b3a3654b13c3dceb15c78664c002fd2f7b2db8e3bc663ff48e9244898",
    "number": 848502,
    "previous": "60792636e3f4b0c272e346b847654265c104ea034ca39fc9227e1199058a3f9e",
    "subblocks": [
        {
            "input_hash": "086a3e603c809b8ec0d1f994606eabf650f2b28e344f4e33f29174be36577367",
            "merkle_leaves": [
                "b6d192e77c67376d58173b73ba2aad3fd02d3558b0bf6020f35b65bd6bfc6d8d"
            ],
            "signatures": [
                {
                    "signature": "db8a49ded2e7cafc0a7a0d411efa9fa423c624925721f677ef8815911e54b4f8b0303f4002bcd2524e00cb16b5d778bf5feaf23d33ab92a5e4d8e9b784829c0d",
                    "signer": "2bdb7a98d65a469dacd93873ce3f8b6bb5284414348cab17ade738f913d35e32"
                },
                {
                    "signature": "dd021d2cfcf2686d0ccc5e2205c82877af8456658da86c3e48a28f6bdb5ff7103b86216ad0610d478db3079e4ca0b2c2acd59fbbf095facfc66c0f06d8a67c0c",
                    "signer": "555100f02ef3bdc469e866140c35955e137624f4a1284bbcb999cd7fb576c869"
                }
            ],
            "subblock": 0,
            "transactions": [
                {
                    "hash": "4f18de4d7b22631e4b86951f35065792cea57be1bb92558d4c06051693a7685b",
                    "result": "Decimal('352.539876326483689528474866275974')",
                    "stamps_used": 128,
                    "state": [
                        {
                            "key": "con_rswp_lst001.balances:a4b1e76899b36cf1817df0b8bdc238552a864ffcf8dd5db87fe7f4dd47395fc5:con_rocketswap_official_v1_1",
                            "value": {
                                "__fixed__": "99999999999999999999999857272.068851418193811764403079539673"
                            }
                        },
                        {
                            "key": "con_rswp_lst001.balances:a4b1e76899b36cf1817df0b8bdc238552a864ffcf8dd5db87fe7f4dd47395fc5",
                            "value": {
                                "__fixed__": "14.017788850781350384294439250153"
                            }
                        },
                        {
                            "key": "con_rswp_lst001.balances:con_rocketswap_official_v1_1",
                            "value": {
                                "__fixed__": "19828638.935110183948483575534140899272"
                            }
                        },
                        {
                            "key": "con_rocketswap_official_v1_1.reserves:con_rswp_lst001",
                            "value": [
                                {
                                    "__fixed__": "2272168.78849026756994206192531067563"
                                },
                                {
                                    "__fixed__": "19713926.077711093948483575534140860237"
                                }
                            ]
                        },
                        {
                            "key": "con_rocketswap_official_v1_1.prices:con_rswp_lst001",
                            "value": {
                                "__fixed__": "0.115257041115682224817981275325"
                            }
                        },
                        {
                            "key": "con_rswp_lst001.balances:burn",
                            "value": {
                                "__fixed__": "720909835.971359044778557324750672712863"
                            }
                        },
                        {
                            "key": "con_rocketswap_official_v1_1.reserves:con_lusd_lst001",
                            "value": [
                                {
                                    "__fixed__": "3674675.57333624736955475514606440908"
                                },
                                {
                                    "__fixed__": "142792.617608687691222332056146215251"
                                }
                            ]
                        },
                        {
                            "key": "con_rocketswap_official_v1_1.prices:con_lusd_lst001",
                            "value": {
                                "__fixed__": "25.734352621831027069635256806633"
                            }
                        },
                        {
                            "key": "currency.balances:a4b1e76899b36cf1817df0b8bdc238552a864ffcf8dd5db87fe7f4dd47395fc5:con_rocketswap_official_v1_1",
                            "value": {
                                "__fixed__": "99999999999999999999997466434.88575577"
                            }
                        },
                        {
                            "key": "currency.balances:a4b1e76899b36cf1817df0b8bdc238552a864ffcf8dd5db87fe7f4dd47395fc5",
                            "value": {
                                "__fixed__": "15996.836291901651693450077990897309"
                            }
                        },
                        {
                            "key": "currency.balances:con_rocketswap_official_v1_1",
                            "value": {
                                "__fixed__": "11652828.005428107345880284319819002091"
                            }
                        },
                        {
                            "key": "con_lusd_lst001.balances:con_rocketswap_official_v1_1",
                            "value": {
                                "__fixed__": "142792.617608687691222332056146219144"
                            }
                        },
                        {
                            "key": "con_lusd_lst001.balances:a4b1e76899b36cf1817df0b8bdc238552a864ffcf8dd5db87fe7f4dd47395fc5",
                            "value": {
                                "__fixed__": "2885.189660003673554718996380459594"
                            }
                        }
                    ],
                    "status": 0,
                    "transaction": {
                        "metadata": {
                            "signature": "a1b8464d5fbe84f7e88b098327df42a9aa49fcc2764041ed7b4883a4de0ed97daa01263d228e9d65b05f0b037748405302729d222473c3a723bfc74c0f50c80e",
                            "timestamp": 1650980787
                        },
                        "payload": {
                            "contract": "con_rocketswap_official_v1_1",
                            "function": "buy",
                            "kwargs": {
                                "contract": "con_lusd_lst001",
                                "currency_amount": {
                                    "__fixed__": "9050"
                                },
                                "minimum_received": {
                                    "__fixed__": "349.876077"
                                },
                                "token_fees": true
                            },
                            "nonce": 1889,
                            "processor": "5b09493df6c18d17cc883ebce54fcb1f5afbd507533417fe32c006009a9c3c4a",
                            "sender": "a4b1e76899b36cf1817df0b8bdc238552a864ffcf8dd5db87fe7f4dd47395fc5",
                            "stamps_supplied": 350
                        }
                    }
                }
            ]
        }
    ]
}