{
    "hash": "da578c01b329854e8d8ce6163ce6f93e7465a435d34e53f2ac6ca9edb6aba4bb",
    "number": 848557,
    "previous": "367b3a9db49e5937bd4ec7e0a4c7e64cb099b0758fea3f442a2dff5b3a596939",
    "subblocks": [
        {
            "input_hash": "eaa31d7a0145191bbaca8e9783e3d086a790de2c9c962e441d70bb965b44240d",
            "merkle_leaves": [
                "d7d99155fd6ebd5697cf82f8573f42ebdfa5ba0898f0953aeb444ce3f1e1ee5d"
            ],
            "signatures": [
                {
                    "signature": "4f4662cb6908bf704ec7e9e1a1dcbc41fd73d8e29e945d8328e006ccfa46452f5eafdab91bbaebaadec6ef498f2547934e557bc977a8359af22ff5b9f474070a",
                    "signer": "2bdb7a98d65a469dacd93873ce3f8b6bb5284414348cab17ade738f913d35e32"
                },
                {
                    "signature": "1cb2f970459ec3bd4ca273c25c216a8fab9504276ec7b5687275322c4c057de96459c18f1d2e35f7a3eb6ac963d8f41a5fddda8e4cf6f3e1996a94945de48806",
                    "signer": "b0fc27299da14bc08834df9c70d73074f3e511a5a91321d4fa413f3401144918"
                }
            ],
            "subblock": 0,
            "transactions": [
                {
                    "hash": "c350f5bfd495ff80b3ec95519dcb4e6bfe3f1af37c527fedd9f190df059af44a",
                    "result": "{'starting_epoch': 124, 'time': 2022-04-26 17:26:12, 'amount': Decimal('513168.292443901022667111546633838598')}",
                    "stamps_used": 128,
                    "state": [
                        {
                            "key": "con_rswp_lst001.balances:b402553b9538625ccab516eaf1f9baafc160c0bc196fc08bac209468a33d8d2c:con_staking_rswp_rswp_interop_v2",
                            "value": {
                                "__fixed__": "99999999999999999999999175587.38415527"
                            }
                        },
                        {
                            "key": "con_rswp_lst001.balances:b402553b9538625ccab516eaf1f9baafc160c0bc196fc08bac209468a33d8d2c",
                            "value": {
                                "__fixed__": "6.110240267104366559349E-9"
                            }
                        },
                        {
                            "key": "con_rswp_lst001.balances:con_staking_rswp_rswp_interop_v2",
                            "value": {
                                "__fixed__": "47786373.649896956707023241306953690671"
                            }
                        },
                        {
                            "key": "con_staking_rswp_rswp_interop_v2.decimal_converter_var",
                            "value": {
                                "__fixed__": "0.009201320641860203064019390398"
                            }
                        },
                        {
                            "key": "con_rswp_lst001.balances:7c296eb80e379171f694a3c5be7640d16f300f09d731c99ac0a92f49c9c0c151",
                            "value": {
                                "__fixed__": "5948063.934660057884266922136555798336"
                            }
                        },
                        {
                            "key": "con_staking_rswp_rswp_interop_v2.StakedBalance",
                            "value": {
                                "__fixed__": "56069910.845212359057788052359169599959"
                            }
                        },
                        {
                            "key": "con_staking_rswp_rswp_interop_v2.WithdrawnBalance",
                            "value": {
                                "__fixed__": "32183537.195315402350764811052215909288"
                            }
                        },
                        {
                            "key": "con_staking_rswp_rswp_interop_v2.balances:b402553b9538625ccab516eaf1f9baafc160c0bc196fc08bac209468a33d8d2c",
                            "value": {
                                "__fixed__": "513168.292443901022667111546633838598"
                            }
                        },
                        {
                            "key": "con_staking_rswp_rswp_interop_v2.Withdrawals:b402553b9538625ccab516eaf1f9baafc160c0bc196fc08bac209468a33d8d2c",
                            "value": 0
                        },
                        {
                            "key": "con_staking_rswp_rswp_interop_v2.Deposits:b402553b9538625ccab516eaf1f9baafc160c0bc196fc08bac209468a33d8d2c",
                            "value": {
                                "amount": {
                                    "__fixed__": "513168.292443901022667111546633838598"
                                },
                                "starting_epoch": 124,
                                "time": {
                                    "__time__": [
                                        2022,
                                        4,
                                        26,
                                        17,
                                        26,
                                        12,
                                        0
                                    ]
                                }
                            }
                        },
                        {
                            "key": "currency.balances:b402553b9538625ccab516eaf1f9baafc160c0bc196fc08bac209468a33d8d2c",
                            "value": {
                                "__fixed__": "291.541836217279690821097284109967"
                            }
                        }
                    ],
                    "status": 0,
                    "transaction": {
                        "metadata": {
                            "signature": "b59627df1a571e5f3e460691c44446bfce3bb56ffda10abc7b24f37acf08832e2988242a910e06530b98c0b2376b7c2345693fdcc8eafb09d5506c718c35310e",
                            "timestamp": 1650993970
                        },
                        "payload": {
                            "contract": "con_staking_rswp_rswp_interop_v2",
                            "function": "addStakingTokens",
                            "kwargs": {
                                "amount": {
                                    "__fixed__": "1576.78046586"
                                }
                            },
                            "nonce": 564,
                            "processor": "5b09493df6c18d17cc883ebce54fcb1f5afbd507533417fe32c006009a9c3c4a",
                            "sender": "b402553b9538625ccab516eaf1f9baafc160c0bc196fc08bac209468a33d8d2c",
                            "stamps_supplied": 533
                        }
                    }
                }
            ]
        }
    ]
}