{
    "hash": "8deec99da0634eb6a892cac8a60968297f2d97024ad0748e4af33243684e4696",
    "number": 848588,
    "previous": "e33c150bcad5e7e5803b1dacfd770b84af39753daf2420ae143cfde7217c6bf1",
    "subblocks": [
        {
            "input_hash": "4ad03070d7c61f8d8b6533483b1c805d4edfcf0a8e1691e02944f418e5611697",
            "merkle_leaves": [
                "6ae2a22cd9be830761aacdb840905005703a28f0b1e36eee3ed7f3b24fbdde31"
            ],
            "signatures": [
                {
                    "signature": "49d1fe8008b7a8c53c54f72f222f6a78c99f2ed07cddbf01fc5f03b10ec50396aaa5d0db6cc5eb211ba300ee9f17b56f7fc1c51935dd0b8f888b987b4084cb02",
                    "signer": "555100f02ef3bdc469e866140c35955e137624f4a1284bbcb999cd7fb576c869"
                },
                {
                    "signature": "525bcea91be6b5fc60c2340915ae206a2f945738ee25ca89156047c54ece0706e17e6924b0578972cb902072bca73c21602718a4ac3f5cb80da756f47b86da00",
                    "signer": "b0fc27299da14bc08834df9c70d73074f3e511a5a91321d4fa413f3401144918"
                }
            ],
            "subblock": 0,
            "transactions": [
                {
                    "hash": "f393680734186e10040898779b105110f466f5f14c470881a864adda07d36b46",
                    "result": "None",
                    "stamps_used": 162,
                    "state": [
                        {
                            "key": "con_liq_mining_mob.decimal_converter_var",
                            "value": {
                                "__fixed__": "0.252950690930470929477780711718"
                            }
                        },
                        {
                            "key": "con_mintorburn.balances:con_liq_mining_mob",
                            "value": {
                                "__fixed__": "499720524.253609020350207240703377132468"
                            }
                        },
                        {
                            "key": "con_mintorburn.total_supply",
                            "value": {
                                "__fixed__": "10482119478.210793883247274358951632324678"
                            }
                        },
                        {
                            "key": "con_mintorburn.balances:ff61544ea94eaaeb5df08ed863c4a938e9129aba6ceee5f31b6681bdede11b89",
                            "value": {
                                "__fixed__": "441082911.902027992128799973354538395329"
                            }
                        },
                        {
                            "key": "con_mintorburn.balances:4b05a3ee6fa1601e6f6b9180afbf23d2def2aa57d5d8b8cb845850887eaedb1c",
                            "value": {
                                "__fixed__": "1888439.898211376544097419376262468389"
                            }
                        },
                        {
                            "key": "con_liq_mining_mob.Withdrawals:4b05a3ee6fa1601e6f6b9180afbf23d2def2aa57d5d8b8cb845850887eaedb1c",
                            "value": {
                                "__fixed__": "2053901.13522173"
                            }
                        },
                        {
                            "key": "con_liq_mining_mob.WithdrawnBalance",
                            "value": {
                                "__fixed__": "500679475.746390979649792759296622867532"
                            }
                        },
                        {
                            "key": "currency.balances:4b05a3ee6fa1601e6f6b9180afbf23d2def2aa57d5d8b8cb845850887eaedb1c",
                            "value": {
                                "__fixed__": "2511.434785798552053349636526279188"
                            }
                        }
                    ],
                    "status": 0,
                    "transaction": {
                        "metadata": {
                            "signature": "1b02d03a53222c350fc62a03376d2ce1471125c77ec526bba9bf64d34e3bd06e0dc0017afe449a28e9da16c6a162f1b81bd3dc3675f94701ff62dd10be366504",
                            "timestamp": 1651001662
                        },
                        "payload": {
                            "contract": "con_liq_mining_mob",
                            "function": "withdrawYield",
                            "kwargs": {
                                "amount": {
                                    "__fixed__": "2053901.13522173"
                                }
                            },
                            "nonce": 817,
                            "processor": "5b09493df6c18d17cc883ebce54fcb1f5afbd507533417fe32c006009a9c3c4a",
                            "sender": "4b05a3ee6fa1601e6f6b9180afbf23d2def2aa57d5d8b8cb845850887eaedb1c",
                            "stamps_supplied": 263
                        }
                    }
                }
            ]
        }
    ]
}